README.md
setup.py
model_tasks/__init__.py
model_tasks_knime.egg-info/PKG-INFO
model_tasks_knime.egg-info/SOURCES.txt
model_tasks_knime.egg-info/dependency_links.txt
model_tasks_knime.egg-info/requires.txt
model_tasks_knime.egg-info/top_level.txt