Metadata-Version: 2.1
Name: model_tasks_knime
Version: 1.0.8
Summary: A light weight command line menu that supports Windows, MacOS, and Linux
Author: ljs
Author-email: 
Keywords: python,menu,dumb_menu,windows,mac,linux
Classifier: Development Status :: 1 - Planning
Classifier: Intended Audience :: Developers
Classifier: Programming Language :: Python :: 3
Classifier: Operating System :: Unix
Classifier: Operating System :: MacOS :: MacOS X
Classifier: Operating System :: Microsoft :: Windows
Requires-Dist: torch
Requires-Dist: numpy
